cavass/__init__.py
cavass/_io.py
cavass/_log.py
cavass/constants.py
cavass/contrast_enhancement.py
cavass/converters.py
cavass/dicom.py
cavass/integration.py
cavass/match.py
cavass/nifti2dicom.py
cavass/ops.py
cavass/slice_range.py
cavass/utils.py
cavass-1.3.0.dist-info/METADATA
cavass-1.3.0.dist-info/WHEEL
cavass-1.3.0.dist-info/RECORD
