Metadata-Version: 2.4
Name: cavass
Version: 1.3.0
Summary: CAVASS Python package.
Author-email: Dai Jian <daijian@stumail.ysu.edu.cn>
License-Expression: MIT
Classifier: Programming Language :: Python :: 3.11
Requires-Python: >=3.11
Requires-Dist: nibabel>=4.0.1
Requires-Dist: numpy>=1.21.0
Requires-Dist: pydicom>=2.4.3
